immuCellAI2/__init__.py
immuCellAI2/myclasses.py
immuCellAI2/myfunction1.py
immuCellAI2/myfunction2.py
immuCellAI2/myfunction3.py
immuCellAI2/myfunction4.py
immuCellAI2/myfunction5.py
immucellai2_0-0.1.0.dist-info/METADATA
immucellai2_0-0.1.0.dist-info/WHEEL
immucellai2_0-0.1.0.dist-info/entry_points.txt
immucellai2_0-0.1.0.dist-info/top_level.txt
immucellai2_0-0.1.0.dist-info/RECORD
