Metadata-Version: 2.4
Name: immuCellAI2.0
Version: 0.1.0
Summary: A tool for gene expression deconvolution
Home-page: https://github.com/yourusername/deconvolution_tool
Author: Yang Jingmin
Author-email: yangjingmin2021@163.com
Classifier: Programming Language :: Python :: 3
Classifier: License :: OSI Approved :: MIT License
Classifier: Operating System :: OS Independent
Requires-Python: >=3.7
Requires-Dist: numpy>=1.20
Requires-Dist: pandas>=1.3
Requires-Dist: openpyxl>=3.0
Requires-Dist: matplotlib>=3.5
